[
    {
        "type":"GENERIC",
        "id": "packaging_medium_cardboard_box_with_wire_barbed",
        "symbol": "]",
        "color": "brown",
        "name": "larger cardboard box (barbed wire)",
        "description": "A medium sized cardboard box, used for reduction in volume. This one is filled with 8 units barbed wire.",
        "price": 200,
        "material": ["paper"],
        "weight": 2816,
        "volume": 12
    },
    {
        "type" : "recipe",
        "result": "packaging_medium_cardboard_box_with_wire_barbed",
        "category": "CC_OTHER",
        "subcategory": "CSC_OTHER_OTHER",
        "skill_used": "fabrication",
        "difficulty": 0,
        "time": 4000,
        "reversible": true,
        "autolearn": true,
        "components": [
            [
                [ "packaging_medium_cardboard_box", 1 ]
            ],
            [
                [ "wire_barbed",                    8 ]
            ]
        ]
    }
]