[
    {
        "type":"GENERIC",
        "id" : "packaging_medium_cardboard_box_with_eyedrops",
        "symbol": "]",
        "color": "brown",
        "name" : "larger cardboard box (saline eye drops)",
        "description": "A medium sized cardboard box, used for reduction in volume. This one is filled with 240 units of saline eye drops.",
        "price": 200,
        "material": ["paper"],
        "weight" : 4720,
        "volume" : 12
    },
    {
        "type" : "recipe",
        "result": "packaging_medium_cardboard_box_with_eyedrops",
        "category": "CC_OTHER",
        "subcategory": "CSC_OTHER_OTHER",
        "skill_used": "fabrication",
        "difficulty": 0,
        "time": 4000,
        "reversible": true,
        "autolearn": true,
        "components": [
            [
                [ "packaging_medium_cardboard_box", 1 ]
            ],
            [
                [ "eyedrops",                       240 ]
            ]
        ]
    }
]