[
  {
    "id": "magic_barrage01",
    "type": "GUN",
    "symbol": "(",
    "color": "yellow",
    "name": "magic barrage",
    "name_plural": "magic barrages",
    "description": "Although it is low power, it is a barrage that fires effectively. It will be very effective for enemies without armor.",
    "price": 10000,
    "material": [ "paper", "wood" ],
    "flags": [ "DURABLE_MELEE", "PRIMITIVE_RANGED_WEAPON" ],
    "skill": "pistol",
    "ammo": "magic_barrage_ammo",
    "weight": 20,
    "volume": 0,
    "durability": 10,
    "armor_data": { "covers": [ "TORSO" ], "coverage": 5, "material_thickness": 1, "encumbrance": 1 },
    "modes": [ [ "DEFAULT", "semi-auto", 1 ], [ "BURST", "2WAY弾", 2 ] ],
    "ranged_damage": 0,
    "range": 6,
    "ammo_effects": [ "CUSTOM_EXPLOSION", "NEVER_JAMS" ],
    "dispersion": 50,
    "sight_dispersion": 20,
    "clip_size": 20,
    "reload": 120
  },
  {
    "id": "minihakkero",
    "type": "GUN",
    "name": "mini hakkero",
    "name_plural": "mini hakkero",
    "description": "Magic item possessed by Marisa. From the transformation of magic, cooking utensils, lucky charms, etc. had many functions. In this world, the work of magic has weakened. Still, it does not change that it is Marisa's treasure.",
    "weight": 650,
    "volume": 1,
    "price": 20000,
    "to_hit": -1,
    "bashing": 2,
    "ammo": "dry_mushroom_magic_powder",
    "material": [ "superalloy" ],
    "symbol": "*",
    "color": "dark_gray",
    "skill": "launcher",
    "range": 30,
    "ranged_damage": 42,
    "pierce": 18,
    "dispersion": 60,
    "sight_dispersion": 80,
    "durability": 8,
    "burst": 2,
    "clip_size": 10,
    "recoil": 150,
    "reload": 700,
    "ammo_effects": [ "LASER", "INCENDIARY", "CUSTOM_EXPLOSION", "NEVER_JAMS" ],
    "flags": [ "TRADER_AVOID", "NEVER_JAMS", "NO_UNLOAD" ]
  },
  {
    "id": "lapis_philosophicus",
    "type": "GUN",
    "name": "philosopher's stone",
    "name_plural": "philosopher's stones",
    "description": "Primal with the power to turn nonmetals into gold. Alchemy is study, thought and philosophy. The quest is linked to black magic, and researchers may learn black magic. Sorcerers may also be explorers.",
    "weight": 880,
    "volume": 1,
    "price": 30000,
    "to_hit": -1,
    "bashing": 4,
    "ammo": "dry_mushroom_magic_powder",
    "material": [ "stone" ],
    "symbol": "*",
    "color": "red",
    "skill": "shotgun",
    "range": 5,
    "ranged_damage": 40,
    "pierce": 8,
    "dispersion": 10,
    "durability": 10,
    "burst": 5,
    "clip_size": 10,
    "recoil": 25,
    "reload": 500,
    "ammo_effects": [ "PLASMA", "INCENDIARY", "SHOT" ],
    "flags": [ "TRADER_AVOID", "NEVER_JAMS", "RELOAD_ONE", "MODE_BURST" ]
  },
  {
    "id": "lapis_philosophicus_nosferatu",
    "type": "GUN",
    "name": "philosopher's stone",
    "name_plural": "philosopher's stones",
    "description": "This equipment is exclusively for monster immortals.",
    "weight": 880,
    "volume": 1,
    "price": 30000,
    "to_hit": -1,
    "bashing": 4,
    "material": [ "stone" ],
    "symbol": "*",
    "color": "red",
    "skill": "launcher",
    "range": 31,
    "ranged_damage": 10,
    "pierce": 8,
    "dispersion": 10,
    "durability": 10,
    "reload": 4,
    "ups_charges": 0,
    "ammo_effects": [ "PLASMA", "INCENDIARY", "SHOT" ],
    "flags": [ "TRADER_AVOID", "NEVER_JAMS" ],
    "modes": [ [ "DEFAULT", "semi-auto", 1 ], [ "BURST", "2 rd.", 2 ] ]
  },
  {
    "type": "ammunition_type",
    "id": "thrown",
    "name": "throwing weapon",
    "default": "throwing_knife"
  },
  {
    "type": "AMMO",
    "id": "throwing_knife",
    "category": "weapons",
    "price": 5200,
    "name": "throwing knife",
    "name_plural": "throwing knives",
    "symbol": ";",
    "color": "light_gray",
    "description": "A thin and flat knife made for throwing.  Its ineffective cutting edge and odd shape makes it unsuitable for use as a tool.",
    "material": "steel",
    "volume": 1,
    "weight": 268,
    "bashing": 1,
    "cutting": 10,
    "thrown_damage": [ { "damage_type": "cut", "amount": 14 } ],
    "ammo_type": "thrown",
    "count": 5,
    "effects": [ "RECOVER_100" ],
    "proportional": { "damage": 12, "pierce": 6 }
  },
  {
    "id": "mon_nosferatu_izayoi_sakuya_gun",
    "type": "GUN",
    "symbol": "o",
    "color": "red",
    "name": "throwing knife",
    "name_plural": "Throwing knives",
    "description": "This is a special equipment for the monster's maid leader.",
    "price": 32400,
    "material": [ "wood" ],
    "flags": [ "TRADER_AVOID", "MODE_BURST" ],
    "skill": "archery",
    "ammo": "thrown",
    "weight": 628,
    "volume": 3,
    "bashing": 6,
    "cutting": 0,
    "pierce": 6,
    "to_hit": -1,
    "ranged_damage": 12,
    "range": 9,
    "dispersion": 110,
    "sight_dispersion": 120,
    "aim_speed": 4,
    "recoil": 225,
    "durability": 6,
    "ammo_effects": [ "NEVER_JAMS" ],
    "modes": [ [ "DEFAULT", "semi-auto", 1 ], [ "BURST", "3 rd.", 3 ] ],
    "clip_size": 60,
    "reload": 30,
    "valid_mod_locations": [
      [ "accessories", 4 ],
      [ "grip", 1 ],
      [ "mechanism", 4 ],
      [ "rail", 1 ],
      [ "sights", 1 ],
      [ "stock", 1 ],
      [ "underbarrel", 1 ]
    ]
  },
  {
    "id": "mon_nosferatu_frandre_scarlet_gun",
    "type": "GUN",
    "name": "revutein",
    "name_plural": "revutein",
    "description": "It is a gun dedicated to Flandre who is a monster.",
    "weight": 1320,
    "volume": 14,
    "price": 970000,
    "to_hit": -1,
    "bashing": 10,
    "symbol": "/",
    "material": [ "superalloy" ],
    "range": 15,
    "ranged_damage": 1,
    "pierce": 60,
    "dispersion": 90,
    "durability": 9,
    "skill": "launcher",
    "ups_charges": 0,
    "aim_speed": 0,
    "ammo_effects": [ "NO_BOOM", "LASER", "INCENDIARY" ],
    "modes": [ [ "DEFAULT", "semi-auto", 1 ], [ "BURST", "5 rd.", 5 ] ],
    "reload": 4,
    "flags": [ "TRADER_AVOID", "NEVER_JAMS" ],
    "valid_mod_locations": [ [ "accessories", 4 ], [ "rail", 1 ], [ "grip", 1 ], [ "stock", 1 ], [ "underbarrel", 1 ] ]
  },
  {
    "id": "golyat_laser_rifle",
    "type": "GUN",
    "name": "Goliath doll laser rifle",
    "name_plural": "Goliath doll laser rifles",
    "description": "It is a laser rifle for Goliath doll.",
    "weight": 2950,
    "volume": 12,
    "price": 1600000,
    "to_hit": -1,
    "bashing": 12,
    "material": [ "steel", "plastic" ],
    "symbol": "(",
    "color": "yellow",
    "skill": "rifle",
    "range": 30,
    "ranged_damage": 52,
    "pierce": 20,
    "dispersion": 10,
    "durability": 8,
    "burst": 2,
    "loudness": 12,
    "ups_charges": 40,
    "reload": 0,
    "valid_mod_locations": [
      [ "accessories", 4 ],
      [ "emitter", 1 ],
      [ "grip", 1 ],
      [ "lens", 1 ],
      [ "rail", 1 ],
      [ "sights", 1 ],
      [ "stock", 1 ],
      [ "underbarrel", 1 ]
    ],
    "ammo_effects": [ "LASER", "INCENDIARY" ],
    "flags": [ "NEVER_JAMS", "NO_UNLOAD" ]
  },
  {
    "id": "sumireko_gun",
    "type": "GUN",
    "reload_noise_volume": 10,
    "name": "The Liberator",
    "name_plural": "Liberators",
    "description": "A handgun that was created from a 3D printer. It's light-blue, giving it the appearance of a toy. But don't be fooled. Those bullets are very real. It can only hold one at a time, though.",
    "weight": "453 g",
    "volume": "1 L",
    "price": 270,
    "to_hit": -2,
    "bashing": 12,
    "material": [ "plastic" ],
    "symbol": "(",
    "color": "light_blue",
    "ammo": "380_p",
    "skill": "handgun",
    "ranged_damage": -1,
    "dispersion": 480,
    "durability": 7,
    "min_cycle_recoil": 1413,
      "valid_mod_locations": [
      [ "accessories", 4 ],
      [ "grip", 1 ],
      [ "mechanism", 4 ],
      [ "rail", 1 ],
      [ "sights", 1 ],
      [ "stock", 1 ]
    ],
    "flags": [ "NEVER_JAMS", "NO_UNLOAD", "RELOAD_ONE"]    
  }
]
